motor-stubs/__init__.pyi
motor-stubs/aiohttp/__init__.pyi
motor-stubs/core.pyi
motor-stubs/docstrings.pyi
motor-stubs/frameworks/asyncio.pyi
motor-stubs/frameworks/tornado.pyi
motor-stubs/metaprogramming.pyi
motor-stubs/motor_asyncio.pyi
motor-stubs/motor_common.pyi
motor-stubs/motor_gridfs.pyi
motor-stubs/motor_tornado.pyi
motor-stubs/web.pyi
motor_types-1.0.0b3.dist-info/LICENSE
motor_types-1.0.0b3.dist-info/METADATA
motor_types-1.0.0b3.dist-info/WHEEL
motor_types-1.0.0b3.dist-info/RECORD
