Metadata-Version: 2.1
Name: motor-types
Version: 1.0.0b3
Summary: Python stubs for Motor, a Non-Blocking MongoDB driver for Python's Tornado and AsyncIO based applications.
Home-page: https://github.com/L0RD-ZER0/Motor-Types
License: MIT
Author: L0RD-ZER0
Author-email: ackerhon@gmail.com
Requires-Python: >=3.8.0,<4.0
Classifier: Development Status :: 4 - Beta
Classifier: Intended Audience :: Developers
Classifier: License :: OSI Approved :: MIT License
Classifier: Programming Language :: Python
Classifier: Programming Language :: Python :: 3
Classifier: Programming Language :: Python :: 3.8
Classifier: Programming Language :: Python :: 3.9
Classifier: Programming Language :: Python :: 3.10
Classifier: Programming Language :: Python :: 3.11
Classifier: Programming Language :: Python :: 3 :: Only
Classifier: Programming Language :: Python :: Implementation :: CPython
Classifier: Topic :: Text Editors
Classifier: Topic :: Utilities
Classifier: Typing :: Stubs Only
Provides-Extra: motor
Requires-Dist: dnspython (>=2.3.0) ; extra == "motor"
Requires-Dist: motor (>=3.0.0) ; extra == "motor"
Requires-Dist: pymongo (>=4.3.0)
Requires-Dist: typing-extensions (>=4.0.0)
Project-URL: Bug Tracker, https://github.com/L0RD-ZER0/Motor-Types/issues
Project-URL: Repository, https://github.com/L0RD-ZER0/Motor-Types
